unicorn_binance_local_depth_cache/cluster_endpoints.cpython-39-x86_64-linux-gnu.so
unicorn_binance_local_depth_cache/cluster.cpython-39-x86_64-linux-gnu.so
unicorn_binance_local_depth_cache/licensing_manager.pyi
unicorn_binance_local_depth_cache/licensing_exceptions.pyi
unicorn_binance_local_depth_cache/manager.pyi
unicorn_binance_local_depth_cache/manager.c
unicorn_binance_local_depth_cache/cluster_endpoints.c
unicorn_binance_local_depth_cache/licensing_manager.c
unicorn_binance_local_depth_cache/cluster_endpoints.py
unicorn_binance_local_depth_cache/licensing_manager.py
unicorn_binance_local_depth_cache/manager.py
unicorn_binance_local_depth_cache/cluster.pyi
unicorn_binance_local_depth_cache/__init__.pyi
unicorn_binance_local_depth_cache/manager.cpython-39-x86_64-linux-gnu.so
unicorn_binance_local_depth_cache/licensing_manager.cpython-39-x86_64-linux-gnu.so
unicorn_binance_local_depth_cache/cluster.py
unicorn_binance_local_depth_cache/licensing_exceptions.c
unicorn_binance_local_depth_cache/exceptions.c
unicorn_binance_local_depth_cache/licensing_exceptions.py
unicorn_binance_local_depth_cache/exceptions.pyi
unicorn_binance_local_depth_cache/cluster.c
unicorn_binance_local_depth_cache/exceptions.py
unicorn_binance_local_depth_cache/exceptions.cpython-39-x86_64-linux-gnu.so
unicorn_binance_local_depth_cache/cluster_endpoints.pyi
unicorn_binance_local_depth_cache/__init__.py
unicorn_binance_local_depth_cache/__init__.cpython-39-x86_64-linux-gnu.so
unicorn_binance_local_depth_cache/__init__.c
unicorn_binance_local_depth_cache/licensing_exceptions.cpython-39-x86_64-linux-gnu.so
unicorn_binance_local_depth_cache-2.8.0.dist-info/top_level.txt
unicorn_binance_local_depth_cache-2.8.0.dist-info/RECORD
unicorn_binance_local_depth_cache-2.8.0.dist-info/METADATA
unicorn_binance_local_depth_cache-2.8.0.dist-info/WHEEL
unicorn_binance_local_depth_cache-2.8.0.dist-info/LICENSE
