Metadata-Version: 2.1
Name: unicorn-binance-local-depth-cache
Version: 2.8.0
Summary: A Python SDK by LUCIT for accessing and managing multiple local Binance order books with Python in a simple, fast, flexible, robust and fully featured way. .
Home-page: https://github.com/LUCIT-Systems-and-Development/unicorn-binance-local-depth-cache
Author: LUCIT Systems and Development
Author-email: info@lucit.tech
License: LSOSL - LUCIT Synergetic Open Source License
Project-URL: Documentation, https://unicorn-binance-local-depth-cache.docs.lucit.tech
Project-URL: Wiki, https://github.com/LUCIT-Systems-and-Development/unicorn-binance-local-depth-cache/wiki
Project-URL: Author, https://www.lucit.tech
Project-URL: Changes, https://unicorn-binance-local-depth-cache.docs.lucit.tech/changelog.html
Project-URL: License, https://unicorn-binance-local-depth-cache.docs.lucit.tech/license.html
Project-URL: Issue Tracker, https://github.com/LUCIT-Systems-and-Development/unicorn-binance-local-depth-cache/issues
Project-URL: Chat, https://gitter.im/unicorn-binance-suite/unicorn-binance-local-depth-cache
Project-URL: Telegram, https://t.me/unicorndevs
Project-URL: Get Support, https://www.lucit.tech/get-support.html
Project-URL: LUCIT Online Shop, https://shop.lucit.services/software
Keywords: binance,depth cache
Classifier: Development Status :: 5 - Production/Stable
Classifier: Programming Language :: Python :: 3.8
Classifier: Programming Language :: Python :: 3.9
Classifier: Programming Language :: Python :: 3.10
Classifier: Programming Language :: Python :: 3.11
Classifier: Programming Language :: Python :: 3.12
Classifier: License :: Other/Proprietary License
Classifier: Intended Audience :: Developers
Classifier: Intended Audience :: Financial and Insurance Industry
Classifier: Intended Audience :: Information Technology
Classifier: Intended Audience :: Science/Research
Classifier: Operating System :: OS Independent
Classifier: Topic :: Office/Business :: Financial :: Investment
Classifier: Topic :: Software Development :: Libraries :: Python Modules
Requires-Python: >=3.8.0
License-File: LICENSE
Requires-Dist: aiohttp
Requires-Dist: lucit-licensing-python>=1.8.2
Requires-Dist: Cython>=3.0.10
Requires-Dist: requests>=2.32.3
Requires-Dist: unicorn-binance-websocket-api>=2.8.1
Requires-Dist: unicorn-binance-rest-api>=2.6.1
